daops/__init__.py
daops/cli.py
daops/processor.py
daops/catalog/__init__.py
daops/catalog/base.py
daops/catalog/intake.py
daops/catalog/util.py
daops/data_utils/__init__.py
daops/data_utils/attr_utils.py
daops/data_utils/common_utils.py
daops/data_utils/coord_utils.py
daops/data_utils/var_utils.py
daops/etc/roocs.ini
daops/fix_utils/decadal_utils.py
daops/ops/__init__.py
daops/ops/average.py
daops/ops/base.py
daops/ops/regrid.py
daops/ops/subset.py
daops/utils/__init__.py
daops/utils/base_lookup.py
daops/utils/common.py
daops/utils/consolidate.py
daops/utils/core.py
daops/utils/fixer.py
daops/utils/normalise.py
daops/utils/testing.py
daops-0.16.0.dist-info/entry_points.txt
daops-0.16.0.dist-info/licenses/LICENSE
daops-0.16.0.dist-info/WHEEL
daops-0.16.0.dist-info/METADATA
daops-0.16.0.dist-info/RECORD
